[
  {
    "chunk_id": 1,
    "text": "To install Redis on AWS, take the following steps: Log into your AWS account and go to Services. In Services, go to Database and select ElastiCache. In the ElastiCache Dashboard, click Create. Choose Cluster engine and specify the basic setup of the cluster as required. You can also define advanced settings by expanding the Advanced Redis Settings tab at the bottom of the page. Note! The Subnet group that the ElastiCache cluster belongs to must be open for access from your MediationZone installation. Open ElastiCache dialog to create an ElastiCache cluster The ElastiCache Dashboard provides you with an overview of your ElastiCache clusters based on type. In addition to creating a cluster in the dashboard, you can also backup, reboot, delete, or modify clusters by selecting the buttons at the top of the dashboard. For further information on creating an ElastiCache cluster, see https://aws.amazon.com/documentation/elasticache/ .",
    "title": "Installation of Redis - MediationZone Documentation 9.4 - InfoZone",
    "url": "https://infozone.atlassian.net/wiki/spaces/MD94/pages/352137100/Installation+of+Redis",
    "word_count": 145,
    "char_count": 940
  }
]