[
  {
    "chunk_id": 1,
    "text": "Below is an example of a customized Data processing report either executed as scheduled or on demand. Audit can be selected on a high level or for each individual file. The balance column gives a view of the current state that is the total number of UDRs into the system minus number of dropped, error system, split and out. Open Example of customized data processing report",
    "title": "Data Processing Reports - MediationZone Documentation 9.4 - InfoZone",
    "url": "https://infozone.atlassian.net/wiki/spaces/MD94/pages/352121380/Data+Processing+Reports",
    "word_count": 66,
    "char_count": 374
  }
]