{
  "id": "wiki__spaces__MD93__pages__204612811__External_-_Sequential_Format",
  "title": "External - Sequential Format - MediationZone Documentation 9.3 - InfoZone",
  "url": "https://infozone.atlassian.net/wiki/spaces/MD93/pages/204612811/External+-+Sequential+Format",
  "categories": [
    "space:MD93"
  ],
  "text": "A sequential external format specification consists of two parts; the record declaration and the field declaration. The record declaration can contain information about UDR size and how the record type is identified. The field declarations may be grouped into larger structures such as bit_block and set . The syntax of the external format declarations is declared as follows: external <format_name> [: <record declaration>] { <content declarations> }; The comma-separated elements of the record declaration list may be (in any order): terminated_by( <terminator> ) dynamic_size( <expression> ) static_size( <constant expression> ) identified_by( <conditional expression> ) The content declarations can be: field declarations bit_block declarations set declarations switched_set declarations This chapter includes the following sections: Record Declaration Field Declarations Expressions",
  "chunks": [
    {
      "chunk_id": 1,
      "text": "A sequential external format specification consists of two parts; the record declaration and the field declaration. The record declaration can contain information about UDR size and how the record type is identified. The field declarations may be grouped into larger structures such as bit_block and set . The syntax of the external format declarations is declared as follows: external <format_name> [: <record declaration>] { <content declarations> }; The comma-separated elements of the record declaration list may be (in any order): terminated_by( <terminator> ) dynamic_size( <expression> ) static_size( <constant expression> ) identified_by( <conditional expression> ) The content declarations can be: field declarations bit_block declarations set declarations switched_set declarations This chapter includes the following sections: Record Declaration Field Declarations Expressions",
      "title": "External - Sequential Format - MediationZone Documentation 9.3 - InfoZone",
      "url": "https://infozone.atlassian.net/wiki/spaces/MD93/pages/204612811/External+-+Sequential+Format",
      "word_count": 118,
      "char_count": 887
    }
  ],
  "metadata": {
    "scraped_at": "2025-06-24T03:36:25.612074",
    "word_count": 118,
    "char_count": 887,
    "chunk_count": 1
  }
}