{
  "id": "wiki__spaces__MD93__pages__204645897__PCC_Routing_Control",
  "title": "PCC Routing Control - MediationZone Documentation 9.3 - InfoZone",
  "url": "https://infozone.atlassian.net/wiki/spaces/MD93/pages/204645897/PCC+Routing+Control",
  "categories": [
    "space:MD93"
  ],
  "text": "Search this document: PCC Routing Control is an extension of the platform from MediationZone and delivers the capability to route and transform real-time data such as Diameter messages. Prerequisites The reader of this document should be familiar with: Diameter Agents For information about the Terms and Abbreviations used in this document, see the Terminology document. Chapters The following chapters and sections are included: Workflow Packages for Routing Control Routing Control Data Model Provisioning for Routing Control",
  "chunks": [
    {
      "chunk_id": 1,
      "text": "Search this document: PCC Routing Control is an extension of the platform from MediationZone and delivers the capability to route and transform real-time data such as Diameter messages. Prerequisites The reader of this document should be familiar with: Diameter Agents For information about the Terms and Abbreviations used in this document, see the Terminology document. Chapters The following chapters and sections are included: Workflow Packages for Routing Control Routing Control Data Model Provisioning for Routing Control",
      "title": "PCC Routing Control - MediationZone Documentation 9.3 - InfoZone",
      "url": "https://infozone.atlassian.net/wiki/spaces/MD93/pages/204645897/PCC+Routing+Control",
      "word_count": 76,
      "char_count": 528
    }
  ],
  "metadata": {
    "scraped_at": "2025-06-24T03:34:57.541726",
    "word_count": 76,
    "char_count": 528,
    "chunk_count": 1
  }
}