{
  "id": "wiki__spaces__MD93__pages__204738255__Categorized_Grouping_Configuration",
  "title": "Categorized Grouping Configuration - MediationZone Documentation 9.3 - InfoZone",
  "url": "https://infozone.atlassian.net/wiki/spaces/MD93/pages/204738255/Categorized+Grouping+Configuration",
  "categories": [
    "space:MD93"
  ],
  "text": "You open the Categorized Grouping agent configuration dialog from a workflow configuration. To open the Categorized Grouping processing agent configuration, click Build  New Configuration . Select Workflow from the Configurations dialog. When prompted to Select workflow type, select Batch . Click Add agent and select Cat group from the Processing tab of the Agent Selection dialog. Open Categorized Grouping agent - Grouping tab Setting Description Setting Description Browse... Select the Browse... button to open the Configuration Selection dialog. Browse for and select the preferred profile to be added to the agent. Force Single UDR If this is disabled the output files will automatically be divided in multiple UDRs per file. The output files will be divided in suitable block sizes.",
  "chunks": [
    {
      "chunk_id": 1,
      "text": "You open the Categorized Grouping agent configuration dialog from a workflow configuration. To open the Categorized Grouping processing agent configuration, click Build  New Configuration . Select Workflow from the Configurations dialog. When prompted to Select workflow type, select Batch . Click Add agent and select Cat group from the Processing tab of the Agent Selection dialog. Open Categorized Grouping agent - Grouping tab Setting Description Setting Description Browse... Select the Browse... button to open the Configuration Selection dialog. Browse for and select the preferred profile to be added to the agent. Force Single UDR If this is disabled the output files will automatically be divided in multiple UDRs per file. The output files will be divided in suitable block sizes.",
      "title": "Categorized Grouping Configuration - MediationZone Documentation 9.3 - InfoZone",
      "url": "https://infozone.atlassian.net/wiki/spaces/MD93/pages/204738255/Categorized+Grouping+Configuration",
      "word_count": 120,
      "char_count": 791
    }
  ],
  "metadata": {
    "scraped_at": "2025-06-24T04:05:43.384599",
    "word_count": 120,
    "char_count": 791,
    "chunk_count": 1
  }
}