{
  "id": "wiki__spaces__MD94__pages__352071957__Extract_Database_Definition_Files_to_SAP_HANA",
  "title": "Extract Database Definition Files to SAP HANA - MediationZone Documentation 9.4 - InfoZone",
  "url": "https://infozone.atlassian.net/wiki/spaces/MD94/pages/352071957/Extract+Database+Definition+Files+to+SAP+HANA",
  "categories": [
    "space:MD94"
  ],
  "text": "When SAP HANA and MediationZone are not installed on the same machine (the database may be installed on any machine within the network), the database definition files need to be transferred to the SAP HANA machine before the database can be created. The database definition files are created in the ./database/saphana subdirectory and archived in the database-setup.tar file. On the SAP HANA machine (as a SAP HANA UNIX user): transfer the database-setup.tar file from the MediationZone machine and extract the files: tar -xvf ./database-setup.tar Enter the database directory : cd database/saphana",
  "chunks": [
    {
      "chunk_id": 1,
      "text": "When SAP HANA and MediationZone are not installed on the same machine (the database may be installed on any machine within the network), the database definition files need to be transferred to the SAP HANA machine before the database can be created. The database definition files are created in the ./database/saphana subdirectory and archived in the database-setup.tar file. On the SAP HANA machine (as a SAP HANA UNIX user): transfer the database-setup.tar file from the MediationZone machine and extract the files: tar -xvf ./database-setup.tar Enter the database directory : cd database/saphana",
      "title": "Extract Database Definition Files to SAP HANA - MediationZone Documentation 9.4 - InfoZone",
      "url": "https://infozone.atlassian.net/wiki/spaces/MD94/pages/352071957/Extract+Database+Definition+Files+to+SAP+HANA",
      "word_count": 91,
      "char_count": 598
    }
  ],
  "metadata": {
    "scraped_at": "2025-06-24T04:15:49.235365",
    "word_count": 91,
    "char_count": 598,
    "chunk_count": 1
  }
}