{
  "id": "wiki__spaces__MD94__pages__352137520__Manage_View",
  "title": "Manage View - MediationZone Documentation 9.4 - InfoZone",
  "url": "https://infozone.atlassian.net/wiki/spaces/MD94/pages/352137520/Manage+View",
  "categories": [
    "space:MD94"
  ],
  "text": "The Manage view contains options for Data Management , Tools, and Monitoring , and you open the view by clicking on the Manage button in the top button bar. When you click on an option, a new screen will open. You can use the Search field to search for a specific option. Open Manage view The following options are available. Data Management Data Management Option Description Aggregation Session Inspector In Aggregation Session Inspector you can view and edit existing aggregation sessions, see Aggregation Session Inspector . Archive Inspector You can use the Archive Inspector to locate files in an archive, see Archive Inspector . Data Hub With Data Hub you can store and query large amounts of data processed by the system, see Data Hub User's Guide Data Veracity You can use Data Veracity when UDRs fail validation and need to be manually handled before they can be successfully processed. With Data Veracity you can examine UDRs, mark them for deletion, force delete them, or update them, see Data Veracity . Duplicate Batch Inspector With the Duplicate Batch Inspector, you can view the metadata cache used for duplicate checking, see Duplicate Batch Agent . Duplicate UDR Inspector With the Duplicate UDR Inspector, you can view UDRs that have been identified as duplicates, see Duplicate UDR Inspector . ECS Inspector Inspect and maintain UDRs and batches in the ECS, see https://infozone.atlassian.net/wiki/x/d0X8F . ECS Statistics Provides statistics on the current number of New and Reprocessed UDRs and batches per Error Code from the ECS, see https://infozone.atlassian.net/wiki/x/kYBvGQ . PCC Buckets With PCC Buckets you can create and manage buckets based on subscriber information. With the PCC Buckets package, buckets can be created and used for usage counting, see PCC Buckets . PCC Extensions With PCC Extensions you can create your own data sets, in addition to the built-in data models for PCC, see PCC Extensions . PCC Policy Control You can use PCC Policy Control to manage PCC rules using the defined rules data model, see PCC Rules . PCC Routing Control With PCC Routing Control you can route and transform real-time data such as Diameter messages, see PCC Routing Control . PCC Usage Management With PCC Usage Management you can provision products in accordance with the defined PCC product sets, see PCC Buckets . Reference Data Management With Reference Data Management you can query and edit specific table sets in relational databases while schema permissions remain unaltered, see Reference Data Management User's Guide . Tools & Monitoring Option Description Access Controller In Access Controller you can define permissions rights for the users of the system, see Access Controller . Alarms and Events Alarms and Events is a monitoring tool that you can use to keep track of the various Alarms and Event Notifications configured in your workflows, see https://infozone.atlassian.net/wiki/spaces/MD94/pages/352073667 and https://infozone.atlassian.net/wiki/spaces/MD94/pages/352073266 . Conditional Trace With Conditional Trace you can troubleshoot active instances, and set up trace filters on agents and UDRs in real-time workflow routes and Analysis agents for either a specific field value or a range of field values, see https://infozone.atlassian.net/wiki/spaces/MD94/pages/352116930 . Configuration Diff Compare two configurations or versions of the same configuration type side by side, see https://infozone.atlassian.net/wiki/x/3_D9F . Configuration Tracer Efficiently restore any deleted configurations and perform troubleshooting activities, see https://infozone.atlassian.net/wiki/x/BACUGQ . EC Groups The EC Groups tool allows you to view and add EC Groups, see https://infozone.atlassian.net/wiki/spaces/MD94/pages/352172346 . Encrypt Password Encrypt Password allows you to encrypt any password and print out the result onto the text field, see https://infozone.atlassian.net/wiki/spaces/MD94/pages/352138473 . Execution Manager Execution Manager allows you to enable, activate, and monitor multiple workflow groups, see https://infozone.atlassian.net/wiki/spaces/MD94/pages/352073880 . Log Files With Log Files, you can access different types of log files, see https://infozone.atlassian.net/wiki/spaces/MD94/pages/352107057 . Log Filter In the Log Filter tool, you can edit log settings for the picos and update the logging dynamically, see https://infozone.atlassian.net/wiki/spaces/MD94/pages/352073916 . Pico Management Create and manage the pico instances, see https://infozone.atlassian.net/wiki/spaces/MD94/pages/352138577 Pico Viewer The Pico Viewer displays a list of all Pico clients currently online in the system, see https://infozone.atlassian.net/wiki/x/Klr9F . Python Manager With Python Manager you manage Python executables, see https://infozone.atlassian.net/wiki/x/yzX9F . System Exporter System Exporter enables you to export data from your system into a ZIP file, a specific directory, an MZ Package (MZP) file, or to Git, see https://infozone.atlassian.net/wiki/spaces/MD94/pages/352074086 . System Importer System Importer enables you to import data to your system, either from a ZIP file, a specific directory, an MZ Package (MZP), or from Git, see https://infozone.atlassian.net/wiki/spaces/MD94/pages/352138799 . System Log System Log stores events and errors that have been registered in the system. In addition, it also handles duplicate events within a time frame. The System Log tool allows you to browse and purge the stored log files, see https://infozone.atlassian.net/wiki/spaces/MD94/pages/352074316 . System Statistics System Statistics collects and consolidates execution information. System Statistics continuously monitors and logs the resource utilization of the different hardware nodes and can provide reports over a given time interval. The throughput of workflows can also be monitored using this mechanism. The statistical information can be viewed graphically over any period, and be printed. See https://infozone.atlassian.net/wiki/spaces/MD94/pages/352107316 . UDR File Editor The UDR File Editor allows you to view and edit the content of UDR files, see https://infozone.atlassian.net/wiki/spaces/MD94/pages/352138893 . Ultra Format Converter The Ultra Format Editor allows you to convert persisted UDRs into an updated UDR format, see https://infozone.atlassian.net/wiki/spaces/MD94/pages/352138893 .",
  "chunks": [
    {
      "chunk_id": 1,
      "text": "The Manage view contains options for Data Management , Tools, and Monitoring , and you open the view by clicking on the Manage button in the top button bar. When you click on an option, a new screen will open. You can use the Search field to search for a specific option. Open Manage view The following options are available. Data Management Data Management Option Description Aggregation Session Inspector In Aggregation Session Inspector you can view and edit existing aggregation sessions, see Aggregation Session Inspector . Archive Inspector You can use the Archive Inspector to locate files in an archive, see Archive Inspector . Data Hub With Data Hub you can store and query large amounts of data processed by the system, see Data Hub User's Guide Data Veracity You can use Data Veracity when UDRs fail validation and need to be manually handled before they can be successfully processed. With Data Veracity you can examine UDRs, mark them for deletion, force delete them, or update them, see Data Veracity . Duplicate Batch Inspector With the Duplicate Batch Inspector, you can view the metadata cache used for duplicate checking, see Duplicate Batch Agent . Duplicate UDR Inspector With the Duplicate UDR Inspector, you can view UDRs that have been identified as duplicates, see Duplicate UDR Inspector . ECS Inspector Inspect and maintain UDRs and batches in the ECS, see https://infozone.atlassian.net/wiki/x/d0X8F . ECS Statistics Provides statistics on the current number of New and Reprocessed UDRs and batches per Error Code from the ECS, see https://infozone.atlassian.net/wiki/x/kYBvGQ . PCC Buckets With PCC Buckets you can create and manage buckets based on subscriber information. With the PCC Buckets package, buckets can be created and used for usage counting, see PCC Buckets . PCC Extensions With PCC Extensions you can create your own data sets, in addition to the built-in data models for PCC, see PCC Extensions . PCC Policy Control You can use PCC Policy Control to manage PCC rules using the defined rules data model, see PCC Rules . PCC Routing Control With PCC Routing Control you can route and transform real-time data such as Diameter messages, see PCC Routing Control . PCC Usage Management With PCC Usage Management you can provision products in accordance with the defined PCC product sets, see PCC Buckets . Reference Data Management With Reference Data Management you can query and edit specific table sets in relational databases while schema permissions remain unaltered, see Reference Data Management User's Guide . Tools & Monitoring Option Description Access Controller In Access Controller you can define permissions rights for the users of the system, see Access Controller . Alarms and Events Alarms and Events is a monitoring tool that you can use to keep track of the various Alarms and Event Notifications configured in your workflows, see https://infozone.atlassian.net/wiki/spaces/MD94/pages/352073667 and https://infozone.atlassian.net/wiki/spaces/MD94/pages/352073266 . Conditional Trace With Conditional Trace you can troubleshoot active instances, and set up trace filters on agents and UDRs in real-time workflow routes and Analysis agents for either a specific field value or a range of field values, see https://infozone.atlassian.net/wiki/spaces/MD94/pages/352116930 . Configuration Diff Compare two configurations or versions of the same configuration type side by side, see https://infozone.atlassian.net/wiki/x/3_D9F . Configuration Tracer Efficiently restore any deleted configurations and perform troubleshooting activities, see https://infozone.atlassian.net/wiki/x/BACUGQ . EC Groups The EC Groups tool allows you to view and add EC Groups, see https://infozone.atlassian.net/wiki/spaces/MD94/pages/352172346 . Encrypt Password Encrypt Password allows you to encrypt any password and print out the result onto the text field, see https://infozone.atlassian.net/wiki/spaces/MD94/pages/352138473 . Execution Manager Execution Manager allows you to enable, activate, and monitor multiple workflow groups, see https://infozone.atlassian.net/wiki/spaces/MD94/pages/352073880 . Log Files With Log Files, you can access different types of log files, see https://infozone.atlassian.net/wiki/spaces/MD94/pages/352107057 . Log Filter In the Log Filter tool, you can edit log settings for the picos and update the logging dynamically, see https://infozone.atlassian.net/wiki/spaces/MD94/pages/352073916 . Pico Management Create and manage the pico instances, see https://infozone.atlassian.net/wiki/spaces/MD94/pages/352138577 Pico Viewer The Pico Viewer displays a list of all Pico clients currently online in the system, see https://infozone.atlassian.net/wiki/x/Klr9F . Python Manager With Python Manager you manage Python executables, see https://infozone.atlassian.net/wiki/x/yzX9F . System Exporter System Exporter enables you to export data from your system into a ZIP file, a specific directory, an MZ Package (MZP) file, or to Git, see https://infozone.atlassian.net/wiki/spaces/MD94/pages/352074086 . System Importer System Importer enables you to import data to your system, either from a ZIP file, a specific directory, an MZ Package (MZP), or from Git, see https://infozone.atlassian.net/wiki/spaces/MD94/pages/352138799 . System Log System Log stores events and errors that have been registered in the system. In addition, it also handles duplicate events within a time frame. The System Log tool allows you to browse and purge the stored log files, see https://infozone.atlassian.net/wiki/spaces/MD94/pages/352074316 . System Statistics System Statistics collects and consolidates execution information. System Statistics continuously monitors and logs the resource utilization of the different hardware nodes and can provide reports over a given time interval. The throughput of workflows can also be monitored using this mechanism. The statistical information can be viewed graphically over any period, and be printed. See https://infozone.atlassian.net/wiki/spaces/MD94/pages/352107316 . UDR File Editor The UDR File Editor allows you to view and edit the content of UDR files, see https://infozone.atlassian.net/wiki/spaces/MD94/pages/352138893 . Ultra Format Converter The Ultra Format Editor allows you to convert persisted UDRs into an updated UDR format, see https://infozone.atlassian.net/wiki/spaces/MD94/pages/352138893 .",
      "title": "Manage View - MediationZone Documentation 9.4 - InfoZone",
      "url": "https://infozone.atlassian.net/wiki/spaces/MD94/pages/352137520/Manage+View",
      "word_count": 884,
      "char_count": 6403
    }
  ],
  "metadata": {
    "scraped_at": "2025-06-24T03:39:28.825553",
    "word_count": 884,
    "char_count": 6403,
    "chunk_count": 1
  }
}