[
  {
    "chunk_id": 1,
    "text": "To use KPI Management, you must install and start Spark, Kafka, and Zookeeper. The following chapters will explain the basic procedures for this, but please refer to the respective pages for details. The versions these instructions and KPI Management have been tested with are: Spark 3.5.0 for Scala 2.13 (the package name is spark-3.5.0-bin-hadoop3-scala2.13.tgz ) Kafka 3.3.2 for Scala 2.13 (the package is kafka_2.13-3.3.2.tgz and that also includes ZooKeeper) This section includes the following subsections: Spark, kafka and zookeeper Starting Clusters and Creating Topics Using Multiple Service Models",
    "title": "KPI Management - External Software - MediationZone Documentation 9.3 - InfoZone",
    "url": "https://infozone.atlassian.net/wiki/spaces/MD93/pages/204677074/KPI+Management+-+External+Software",
    "word_count": 88,
    "char_count": 607
  }
]